cupoch-0.2.11.0.data/purelib/cupoch/__init__.py
cupoch-0.2.11.0.data/purelib/cupoch/cupoch.cp311-win_amd64.pyd
cupoch-0.2.11.0.dist-info/LICENSE.txt
cupoch-0.2.11.0.dist-info/METADATA
cupoch-0.2.11.0.dist-info/WHEEL
cupoch-0.2.11.0.dist-info/top_level.txt
cupoch-0.2.11.0.dist-info/RECORD
