Metadata-Version: 2.1
Name: cupoch
Version: 0.2.11.0
Summary: ['Cupoch: Robotics with GPU computing']
Home-page: https://github.com/neka-nat/cupoch
Author: neka-nat
Author-email: nekanat.stock@gmail.com
License: MIT
Project-URL: Documentation, https://github.com/neka-nat/cupoch
Project-URL: Source code, https://github.com/neka-nat/cupoch
Project-URL: Issues, https://github.com/neka-nat/cupoch/issues
Keywords: robotics point-cloud mesh RGB-D collision visualization
Classifier: Development Status :: 3 - Alpha
Classifier: Environment :: Win32 (MS Windows)
Classifier: Environment :: X11 Applications
Classifier: Framework :: Robot Framework
Classifier: Framework :: Robot Framework :: Library
Classifier: Framework :: Robot Framework :: Tool
Classifier: Intended Audience :: Developers
Classifier: Intended Audience :: Education
Classifier: Intended Audience :: Other Audience
Classifier: Intended Audience :: Science/Research
Classifier: License :: OSI Approved :: MIT License
Classifier: Natural Language :: English
Classifier: Operating System :: POSIX :: Linux
Classifier: Programming Language :: C
Classifier: Programming Language :: C++
Classifier: Programming Language :: Python :: 3
Classifier: Programming Language :: Python :: 3.9
Classifier: Programming Language :: Python :: 3.10
Classifier: Programming Language :: Python :: 3.11
Classifier: Programming Language :: Python :: 3.12
Classifier: Topic :: Education
Classifier: Topic :: Multimedia :: Graphics :: 3D Rendering
Classifier: Topic :: Multimedia :: Graphics :: Viewers
Classifier: Topic :: Scientific/Engineering
Classifier: Topic :: Scientific/Engineering :: Mathematics
Classifier: Topic :: Scientific/Engineering :: Visualization
Classifier: Topic :: Software Development :: Libraries :: Python Modules
Classifier: Topic :: Utilities
License-File: LICENSE.txt
Requires-Dist: numpy
Requires-Dist: wheel
